[
  {
    "client": "Compex FE",
    "project": "Daily Productivity",
    "report": "CompexFLC_Prediction.xlsx",
    "filename": "CompexFLC_Prediction.xlsx",
    "date": "2025-09-11",
    "time": "09:12 AM",
    "validationStatus": "Success",
    "errorLog": ""
  },
  {
    "client": "Compex FE",
    "project": "Completes",
    "report": "CompexFLC_Completes.xlsx",
    "filename": "CompexFLC_Completes.xlsx",
    "date": "2025-09-14",
    "time": "10:53 AM",
    "validationStatus": "Success",
    "errorLog": ""
  },
  {
    "client": "Compex CI",
    "project": "Gross Wallet",
    "report": "CompexFLC_GWallet.xlsx",
    "filename": "CompexFLC_GWallet.xlsx",
    "date": "2025-09-14",
    "time": "11:02 AM",
    "validationStatus": "Success",
    "errorLog": ""
  },
  {
    "client": "Compex TLC",
    "project": "Total Contracts",
    "report": "CompexFLC_TContracts.xlsx",
    "filename": "CompexFLC_TContracts.xlsx",
    "date": "2025-09-14",
    "time": "12:14 PM",
    "validationStatus": "Failed",
    "errorLog": "Validation error: Missing columns"
  },
  {
    "client": "Compex OE",
    "project": "OT Inventory",
    "report": "CompexFLC_Inventory.xlsx",
    "filename": "CompexFLC_Inventory.xlsx",
    "date": "2025-08-11",
    "time": "09:45 AM",
    "validationStatus": "Failed",
    "errorLog": "File format not supported"
  },
  {
    "client": "Compex eE",
    "project": "OT Inventory",
    "report": "CompexFLC_Inventory.xlsx",
    "filename": "CompexFLC_Inventory.xlsx",
    "date": "2025-08-11",
    "time": "09:45 AM",
    "validationStatus": "Failed",
    "errorLog": "File format not supported"
  }
]
